{"0tmT0uM9X7qPqvsQL$Vnrv": {"type": "window", "global_corners": [[0.35, 2.12, -2.1], [1.35, 2.12, -2.1], [1.35, 2.19, -2.1], [0.35, 2.19, -2.1], [0.35, 2.12, -0.6], [1.35, 2.12, -0.6], [1.35, 2.19, -0.6], [0.35, 2.19, -0.6]], "belongs_to": "3UEb2iq7D2tOgbX6Mufs$X"}, "0DL0We4nPFyAVGrKFIo$_Q": {"type": "window", "global_corners": [[4.75, 2.12, -2.1], [5.75, 2.12, -2.1], [5.75, 2.19, -2.1], [4.75, 2.19, -2.1], [4.75, 2.12, -0.6], [5.75, 2.12, -0.6], [5.75, 2.19, -0.6], [4.75, 2.19, -0.6]], "belongs_to": "3UEb2iq7D2tOgbX6Mufs$X"}, "0l4dSq$O1EhPrwBM112bpI": {"type": "window", "global_corners": [[3.25, 2.12, -2.1], [4.25, 2.12, -2.1], [4.25, 2.19, -2.1], [3.25, 2.19, -2.1], [3.25, 2.12, -0.6], [4.25, 2.12, -0.6], [4.25, 2.19, -0.6], [3.25, 2.19, -0.6]], "belongs_to": "3UEb2iq7D2tOgbX6Mufs$X"}, "1pje_D_or3NPRN0K90aQGI": {"type": "window", "global_corners": [[1.75, 2.12, -2.1], [2.75, 2.12, -2.1], [2.75, 2.19, -2.1], [1.75, 2.19, -2.1], [1.75, 2.12, -0.6], [2.75, 2.12, -0.6], [2.75, 2.19, -0.6], [1.75, 2.19, -0.6]], "belongs_to": "3UEb2iq7D2tOgbX6Mufs$X"}, "0UvsYD1LfBsx91MU4B1EY1": {"type": "window", "global_corners": [[10.75, 2.12, -2.1], [11.75, 2.12, -2.1], [11.75, 2.19, -2.1], [10.75, 2.19, -2.1], [10.75, 2.12, -0.6], [11.75, 2.12, -0.6], [11.75, 2.19, -0.6], [10.75, 2.19, -0.6]], "belongs_to": "2xcLNHPon6VO6wB_n0EQLF"}, "2XgPE753r1of9qIx7CUdRU": {"type": "window", "global_corners": [[9.25, 2.12, -2.1], [10.25, 2.12, -2.1], [10.25, 2.19, -2.1], [9.25, 2.19, -2.1], [9.25, 2.12, -0.6], [10.25, 2.12, -0.6], [10.25, 2.19, -0.6], [9.25, 2.19, -0.6]], "belongs_to": "2xcLNHPon6VO6wB_n0EQLF"}, "3pwwIpoc57hgvawYgQG32b": {"type": "window", "global_corners": [[7.75, 2.12, -2.1], [8.75, 2.12, -2.1], [8.75, 2.19, -2.1], [7.75, 2.19, -2.1], [7.75, 2.12, -0.6], [8.75, 2.12, -0.6], [8.75, 2.19, -0.6], [7.75, 2.19, -0.6]], "belongs_to": "2xcLNHPon6VO6wB_n0EQLF"}, "1cHXMbICn1WhQfo8g2ZwtI": {"type": "window", "global_corners": [[6.25, 2.12, -2.1], [7.25, 2.12, -2.1], [7.25, 2.19, -2.1], [6.25, 2.19, -2.1], [6.25, 2.12, -0.6], [7.25, 2.12, -0.6], [7.25, 2.19, -0.6], [6.25, 2.19, -0.6]], "belongs_to": "2xcLNHPon6VO6wB_n0EQLF"}, "1ouI6iS8H4iveeYlQVR6wM": {"type": "window", "global_corners": [[13.75, 2.12, -2.1], [14.75, 2.12, -2.1], [14.75, 2.19, -2.1], [13.75, 2.19, -2.1], [13.75, 2.12, -0.6], [14.75, 2.12, -0.6], [14.75, 2.19, -0.6], [13.75, 2.19, -0.6]], "belongs_to": "2Hh$tXimL1_Aogi9jn1cZ4"}, "3lUU1BV1T9OeboWPSlTSt6": {"type": "window", "global_corners": [[12.25, 2.12, -2.1], [13.25, 2.12, -2.1], [13.25, 2.19, -2.1], [12.25, 2.19, -2.1], [12.25, 2.12, -0.6], [13.25, 2.12, -0.6], [13.25, 2.19, -0.6], [12.25, 2.19, -0.6]], "belongs_to": "2Hh$tXimL1_Aogi9jn1cZ4"}, "2UkFRzvxv6r8FK6VLY_xj2": {"type": "window", "global_corners": [[27.25, 2.12, -2.1], [28.25, 2.12, -2.1], [28.25, 2.19, -2.1], [27.25, 2.19, -2.1], [27.25, 2.12, -0.6], [28.25, 2.12, -0.6], [28.25, 2.19, -0.6], [27.25, 2.19, -0.6]], "belongs_to": "0V74RtuUH1zQt_CcawQbBc"}, "3YVQQ7t1vFE8ej$paGzJX9": {"type": "window", "global_corners": [[28.75, 2.12, -2.1], [29.75, 2.12, -2.1], [29.75, 2.19, -2.1], [28.75, 2.19, -2.1], [28.75, 2.12, -0.6], [29.75, 2.12, -0.6], [29.75, 2.19, -0.6], [28.75, 2.19, -0.6]], "belongs_to": "0V74RtuUH1zQt_CcawQbBc"}, "3NpTHgn_j3zx2eDS5wHeXw": {"type": "window", "global_corners": [[40.65, 13.81, -2.1], [41.65, 13.81, -2.1], [41.65, 13.88, -2.1], [40.65, 13.88, -2.1], [40.65, 13.81, -0.6], [41.65, 13.81, -0.6], [41.65, 13.88, -0.6], [40.65, 13.88, -0.6]], "belongs_to": "0dXE$xLxz8MwbtYoTqJPiO"}, "0U9x4f675CxAXlkJBnOQjW": {"type": "window", "global_corners": [[39.25, 13.81, -2.1], [40.25, 13.81, -2.1], [40.25, 13.88, -2.1], [39.25, 13.88, -2.1], [39.25, 13.81, -0.6], [40.25, 13.81, -0.6], [40.25, 13.88, -0.6], [39.25, 13.88, -0.6]], "belongs_to": "0dXE$xLxz8MwbtYoTqJPiO"}, "350CUI1c1F0QSJPiZz1wP5": {"type": "window", "global_corners": [[37.75, 13.81, -2.1], [38.75, 13.81, -2.1], [38.75, 13.88, -2.1], [37.75, 13.88, -2.1], [37.75, 13.81, -0.6], [38.75, 13.81, -0.6], [38.75, 13.88, -0.6], [37.75, 13.88, -0.6]], "belongs_to": "0dXE$xLxz8MwbtYoTqJPiO"}, "1xVAErrPn9h9PZS4j$g3G8": {"type": "window", "global_corners": [[36.25, 13.81, -2.1], [37.25, 13.81, -2.1], [37.25, 13.88, -2.1], [36.25, 13.88, -2.1], [36.25, 13.81, -0.6], [37.25, 13.81, -0.6], [37.25, 13.88, -0.6], [36.25, 13.88, -0.6]], "belongs_to": "0dXE$xLxz8MwbtYoTqJPiO"}, "3I0_zAKh53_PRDghNrS9dg": {"type": "window", "global_corners": [[34.75, 13.81, -2.1], [35.75, 13.81, -2.1], [35.75, 13.88, -2.1], [34.75, 13.88, -2.1], [34.75, 13.81, -0.6], [35.75, 13.81, -0.6], [35.75, 13.88, -0.6], [34.75, 13.88, -0.6]], "belongs_to": "0dXE$xLxz8MwbtYoTqJPiO"}, "1OV17CuXX2yOi2aX$NydU3": {"type": "window", "global_corners": [[33.25, 13.81, -2.1], [34.25, 13.81, -2.1], [34.25, 13.88, -2.1], [33.25, 13.88, -2.1], [33.25, 13.81, -0.6], [34.25, 13.81, -0.6], [34.25, 13.88, -0.6], [33.25, 13.88, -0.6]], "belongs_to": "0dXE$xLxz8MwbtYoTqJPiO"}, "0DyvKRpqrDchZau$PoLIcs": {"type": "window", "global_corners": [[31.75, 13.81, -2.1], [32.75, 13.81, -2.1], [32.75, 13.88, -2.1], [31.75, 13.88, -2.1], [31.75, 13.81, -0.6], [32.75, 13.81, -0.6], [32.75, 13.88, -0.6], [31.75, 13.88, -0.6]], "belongs_to": "0dXE$xLxz8MwbtYoTqJPiO"}, "1OeButDUzCWPGfp3wmTIEe": {"type": "window", "global_corners": [[30.25, 13.81, -2.1], [31.25, 13.81, -2.1], [31.25, 13.88, -2.1], [30.25, 13.88, -2.1], [30.25, 13.81, -0.6], [31.25, 13.81, -0.6], [31.25, 13.88, -0.6], [30.25, 13.88, -0.6]], "belongs_to": "0dXE$xLxz8MwbtYoTqJPiO"}, "3ddBeFeQz9QvQv9xPTOCTk": {"type": "window", "global_corners": [[40.65, 2.12, -2.1], [41.65, 2.12, -2.1], [41.65, 2.19, -2.1], [40.65, 2.19, -2.1], [40.65, 2.12, -0.6], [41.65, 2.12, -0.6], [41.65, 2.19, -0.6], [40.65, 2.19, -0.6]], "belongs_to": "0dXE$xLxz8MwbtYoTqJPiO"}, "1Wa4Z7NrXAHwCBRQNj0Cft": {"type": "window", "global_corners": [[39.25, 2.12, -2.1], [40.25, 2.12, -2.1], [40.25, 2.19, -2.1], [39.25, 2.19, -2.1], [39.25, 2.12, -0.6], [40.25, 2.12, -0.6], [40.25, 2.19, -0.6], [39.25, 2.19, -0.6]], "belongs_to": "0dXE$xLxz8MwbtYoTqJPiO"}, "2HUtvXxkDFoO6CX6ZGSxv2": {"type": "window", "global_corners": [[37.75, 2.12, -2.1], [38.75, 2.12, -2.1], [38.75, 2.19, -2.1], [37.75, 2.19, -2.1], [37.75, 2.12, -0.6], [38.75, 2.12, -0.6], [38.75, 2.19, -0.6], [37.75, 2.19, -0.6]], "belongs_to": "0dXE$xLxz8MwbtYoTqJPiO"}, "3hnGLaSkH3SvHIeUtURa3P": {"type": "window", "global_corners": [[36.25, 2.12, -2.1], [37.25, 2.12, -2.1], [37.25, 2.19, -2.1], [36.25, 2.19, -2.1], [36.25, 2.12, -0.6], [37.25, 2.12, -0.6], [37.25, 2.19, -0.6], [36.25, 2.19, -0.6]], "belongs_to": "0dXE$xLxz8MwbtYoTqJPiO"}, "2r5uaVzi56I8umPPBXAgku": {"type": "window", "global_corners": [[34.75, 2.12, -2.1], [35.75, 2.12, -2.1], [35.75, 2.19, -2.1], [34.75, 2.19, -2.1], [34.75, 2.12, -0.6], [35.75, 2.12, -0.6], [35.75, 2.19, -0.6], [34.75, 2.19, -0.6]], "belongs_to": "0dXE$xLxz8MwbtYoTqJPiO"}, "3QEUKhewj50vykoqwkHQYg": {"type": "window", "global_corners": [[33.25, 2.12, -2.1], [34.25, 2.12, -2.1], [34.25, 2.19, -2.1], [33.25, 2.19, -2.1], [33.25, 2.12, -0.6], [34.25, 2.12, -0.6], [34.25, 2.19, -0.6], [33.25, 2.19, -0.6]], "belongs_to": "0dXE$xLxz8MwbtYoTqJPiO"}, "0OmtQ6_NzE188dQC34v0g6": {"type": "window", "global_corners": [[31.75, 2.12, -2.1], [32.75, 2.12, -2.1], [32.75, 2.19, -2.1], [31.75, 2.19, -2.1], [31.75, 2.12, -0.6], [32.75, 2.12, -0.6], [32.75, 2.19, -0.6], [31.75, 2.19, -0.6]], "belongs_to": "0dXE$xLxz8MwbtYoTqJPiO"}, "27_DcwcBj4pR51s85xqpTA": {"type": "window", "global_corners": [[30.25, 2.12, -2.1], [31.25, 2.12, -2.1], [31.25, 2.19, -2.1], [30.25, 2.19, -2.1], [30.25, 2.12, -0.6], [31.25, 2.12, -0.6], [31.25, 2.19, -0.6], [30.25, 2.19, -0.6]], "belongs_to": "0dXE$xLxz8MwbtYoTqJPiO"}, "2KWGkABzf5YuhLq7$mydKO": {"type": "window", "global_corners": [[28.75, 13.81, -2.1], [29.75, 13.81, -2.1], [29.75, 13.88, -2.1], [28.75, 13.88, -2.1], [28.75, 13.81, -0.6], [29.75, 13.81, -0.6], [29.75, 13.88, -0.6], [28.75, 13.88, -0.6]], "belongs_to": "2G3Zgh3YLFBxViczryC8tv"}, "15lQJrYf9A4xrsK9Ca$fEc": {"type": "window", "global_corners": [[27.25, 13.81, -2.1], [28.25, 13.81, -2.1], [28.25, 13.88, -2.1], [27.25, 13.88, -2.1], [27.25, 13.81, -0.6], [28.25, 13.81, -0.6], [28.25, 13.88, -0.6], [27.25, 13.88, -0.6]], "belongs_to": "2G3Zgh3YLFBxViczryC8tv"}, "3DDIxElIvCmOW6piyS2d1Q": {"type": "window", "global_corners": [[24.25, 13.81, -2.1], [25.25, 13.81, -2.1], [25.25, 13.88, -2.1], [24.25, 13.88, -2.1], [24.25, 13.81, -0.6], [25.25, 13.81, -0.6], [25.25, 13.88, -0.6], [24.25, 13.88, -0.6]], "belongs_to": "1pG7ErnqL79fYOSoJhY$mD"}, "37DmcwHRH46vMkO0bCgirD": {"type": "window", "global_corners": [[25.75, 13.81, -2.1], [26.75, 13.81, -2.1], [26.75, 13.88, -2.1], [25.75, 13.88, -2.1], [25.75, 13.81, -0.6], [26.75, 13.81, -0.6], [26.75, 13.88, -0.6], [25.75, 13.88, -0.6]], "belongs_to": "1pG7ErnqL79fYOSoJhY$mD"}, "24$uaJIhH2ouGJkH7Wd6Cg": {"type": "window", "global_corners": [[13.75, 13.81, -2.1], [14.75, 13.81, -2.1], [14.75, 13.88, -2.1], [13.75, 13.88, -2.1], [13.75, 13.81, -0.6], [14.75, 13.81, -0.6], [14.75, 13.88, -0.6], [13.75, 13.88, -0.6]], "belongs_to": "2NO$Il8fr1n8x3zsU1IoYc"}, "2vt0LWwZ1B$wvl1xJ$rRYX": {"type": "window", "global_corners": [[12.25, 13.81, -2.1], [13.25, 13.81, -2.1], [13.25, 13.88, -2.1], [12.25, 13.88, -2.1], [12.25, 13.81, -0.6], [13.25, 13.81, -0.6], [13.25, 13.88, -0.6], [12.25, 13.88, -0.6]], "belongs_to": "2NO$Il8fr1n8x3zsU1IoYc"}, "3LhgbZxOfBS96L3z1ugkAf": {"type": "window", "global_corners": [[10.75, 13.81, -2.1], [11.75, 13.81, -2.1], [11.75, 13.88, -2.1], [10.75, 13.88, -2.1], [10.75, 13.81, -0.6], [11.75, 13.81, -0.6], [11.75, 13.88, -0.6], [10.75, 13.88, -0.6]], "belongs_to": "3vTaz$m4D7Mw20Cj4ZCMEW"}, "0M5DbO6eLEYAljcKYr52lj": {"type": "window", "global_corners": [[9.25, 13.81, -2.1], [10.25, 13.81, -2.1], [10.25, 13.88, -2.1], [9.25, 13.88, -2.1], [9.25, 13.81, -0.6], [10.25, 13.81, -0.6], [10.25, 13.88, -0.6], [9.25, 13.88, -0.6]], "belongs_to": "3vTaz$m4D7Mw20Cj4ZCMEW"}, "0ha9$dzvr5hfHL2tup2bF9": {"type": "window", "global_corners": [[7.75, 13.81, -2.1], [8.75, 13.81, -2.1], [8.75, 13.88, -2.1], [7.75, 13.88, -2.1], [7.75, 13.81, -0.6], [8.75, 13.81, -0.6], [8.75, 13.88, -0.6], [7.75, 13.88, -0.6]], "belongs_to": "29dtO28k16G9baf14UO37j"}, "2Luo2PAnn99uT1hjBk4Vyq": {"type": "window", "global_corners": [[6.25, 13.81, -2.1], [7.25, 13.81, -2.1], [7.25, 13.88, -2.1], [6.25, 13.88, -2.1], [6.25, 13.81, -0.6], [7.25, 13.81, -0.6], [7.25, 13.88, -0.6], [6.25, 13.88, -0.6]], "belongs_to": "29dtO28k16G9baf14UO37j"}, "2R1TAx1CP0iABwkslb$Gv_": {"type": "window", "global_corners": [[4.75, 13.81, -2.1], [5.75, 13.81, -2.1], [5.75, 13.88, -2.1], [4.75, 13.88, -2.1], [4.75, 13.81, -0.6], [5.75, 13.81, -0.6], [5.75, 13.88, -0.6], [4.75, 13.88, -0.6]], "belongs_to": "3YOWN6kp53UhVDk7gccfjD"}, "3fHoF9ddLDNg7p4qo0Wq7v": {"type": "window", "global_corners": [[3.25, 13.81, -2.1], [4.25, 13.81, -2.1], [4.25, 13.88, -2.1], [3.25, 13.88, -2.1], [3.25, 13.81, -0.6], [4.25, 13.81, -0.6], [4.25, 13.88, -0.6], [3.25, 13.88, -0.6]], "belongs_to": "3YOWN6kp53UhVDk7gccfjD"}, "3ZiHV_RFL3shDKRIJ1fjqB": {"type": "window", "global_corners": [[0.35, 13.81, -2.1], [1.35, 13.81, -2.1], [1.35, 13.88, -2.1], [0.35, 13.88, -2.1], [0.35, 13.81, -0.6], [1.35, 13.81, -0.6], [1.35, 13.88, -0.6], [0.35, 13.88, -0.6]], "belongs_to": "25NDKbpWH5r94ho13fJMeb"}, "3xvQAmf45C8PC3qSvtvqlg": {"type": "window", "global_corners": [[1.75, 13.81, -2.1], [2.75, 13.81, -2.1], [2.75, 13.88, -2.1], [1.75, 13.88, -2.1], [1.75, 13.81, -0.6], [2.75, 13.81, -0.6], [2.75, 13.88, -0.6], [1.75, 13.88, -0.6]], "belongs_to": "25NDKbpWH5r94ho13fJMeb"}, "3CiCcmHpP2K84bQMGsx3y3": {"type": "window", "global_corners": [[16.75, 13.81, -2.1], [17.75, 13.81, -2.1], [17.75, 13.88, -2.1], [16.75, 13.88, -2.1], [16.75, 13.81, -0.6], [17.75, 13.81, -0.6], [17.75, 13.88, -0.6], [16.75, 13.88, -0.6]], "belongs_to": "1nsRm1QQb1xwWpzzFR7Ax3"}, "1_UD$NAdH5j8VQ4M152ONb": {"type": "window", "global_corners": [[15.25, 13.81, -2.1], [16.25, 13.81, -2.1], [16.25, 13.88, -2.1], [15.25, 13.88, -2.1], [15.25, 13.81, -0.6], [16.25, 13.81, -0.6], [16.25, 13.88, -0.6], [15.25, 13.88, -0.6]], "belongs_to": "1nsRm1QQb1xwWpzzFR7Ax3"}, "0CGHrXiHv4HBY05$ose5V2": {"type": "window", "global_corners": [[0.35, 2.12, 0.9], [1.35, 2.12, 0.9], [1.35, 2.19, 0.9], [0.35, 2.19, 0.9], [0.35, 2.12, 2.4], [1.35, 2.12, 2.4], [1.35, 2.19, 2.4], [0.35, 2.19, 2.4]], "belongs_to": "3EN96kdYDB2OOGjNLp8e86"}, "3_CZje0qzFFfsJdg65CoF_": {"type": "window", "global_corners": [[1.75, 2.12, 0.9], [2.75, 2.12, 0.9], [2.75, 2.19, 0.9], [1.75, 2.19, 0.9], [1.75, 2.12, 2.4], [2.75, 2.12, 2.4], [2.75, 2.19, 2.4], [1.75, 2.19, 2.4]], "belongs_to": "3EN96kdYDB2OOGjNLp8e86"}, "38g7R7wXv17gWe71J1QVvg": {"type": "window", "global_corners": [[7.75, 2.12, 0.9], [8.75, 2.12, 0.9], [8.75, 2.19, 0.9], [7.75, 2.19, 0.9], [7.75, 2.12, 2.4], [8.75, 2.12, 2.4], [8.75, 2.19, 2.4], [7.75, 2.19, 2.4]], "belongs_to": "1_Evy7T$DCiwLgTMLHCRoe"}, "0ChVXF3Lj3cv66fcKII9ok": {"type": "window", "global_corners": [[6.25, 2.12, 0.9], [7.25, 2.12, 0.9], [7.25, 2.19, 0.9], [6.25, 2.19, 0.9], [6.25, 2.12, 2.4], [7.25, 2.12, 2.4], [7.25, 2.19, 2.4], [6.25, 2.19, 2.4]], "belongs_to": "1_Evy7T$DCiwLgTMLHCRoe"}, "23NwekTZP52g8Rswy$C86L": {"type": "window", "global_corners": [[4.75, 2.12, 0.9], [5.75, 2.12, 0.9], [5.75, 2.19, 0.9], [4.75, 2.19, 0.9], [4.75, 2.12, 2.4], [5.75, 2.12, 2.4], [5.75, 2.19, 2.4], [4.75, 2.19, 2.4]], "belongs_to": "1_Evy7T$DCiwLgTMLHCRoe"}, "2fB1Cm3Gn6SRIusC52HTGe": {"type": "window", "global_corners": [[3.25, 2.12, 0.9], [4.25, 2.12, 0.9], [4.25, 2.19, 0.9], [3.25, 2.19, 0.9], [3.25, 2.12, 2.4], [4.25, 2.12, 2.4], [4.25, 2.19, 2.4], [3.25, 2.19, 2.4]], "belongs_to": "1_Evy7T$DCiwLgTMLHCRoe"}, "2SkcgVRZT55eBv9ib8QmcA": {"type": "window", "global_corners": [[13.75, 2.12, 0.9], [14.75, 2.12, 0.9], [14.75, 2.19, 0.9], [13.75, 2.19, 0.9], [13.75, 2.12, 2.4], [14.75, 2.12, 2.4], [14.75, 2.19, 2.4], [13.75, 2.19, 2.4]], "belongs_to": "3eQ_MQ5er5UeRXq4xxAoKl"}, "0MhDBT4Xn35BdD0XgN2Zqz": {"type": "window", "global_corners": [[12.25, 2.12, 0.9], [13.25, 2.12, 0.9], [13.25, 2.19, 0.9], [12.25, 2.19, 0.9], [12.25, 2.12, 2.4], [13.25, 2.12, 2.4], [13.25, 2.19, 2.4], [12.25, 2.19, 2.4]], "belongs_to": "3eQ_MQ5er5UeRXq4xxAoKl"}, "3c$Xo8yh56dgtfpqOlOZSt": {"type": "window", "global_corners": [[10.75, 2.12, 0.9], [11.75, 2.12, 0.9], [11.75, 2.19, 0.9], [10.75, 2.19, 0.9], [10.75, 2.12, 2.4], [11.75, 2.12, 2.4], [11.75, 2.19, 2.4], [10.75, 2.19, 2.4]], "belongs_to": "3eQ_MQ5er5UeRXq4xxAoKl"}, "3cfqOXb3f3Ow95PuTGA8ge": {"type": "window", "global_corners": [[9.25, 2.12, 0.9], [10.25, 2.12, 0.9], [10.25, 2.19, 0.9], [9.25, 2.19, 0.9], [9.25, 2.12, 2.4], [10.25, 2.12, 2.4], [10.25, 2.19, 2.4], [9.25, 2.19, 2.4]], "belongs_to": "3eQ_MQ5er5UeRXq4xxAoKl"}, "1$wm4f6k99XRQrMNEvL_1P": {"type": "window", "global_corners": [[0.12, 7.55, 0.9], [0.19, 7.55, 0.9], [0.19, 8.45, 0.9], [0.12, 8.45, 0.9], [0.12, 7.55, 2.4], [0.19, 7.55, 2.4], [0.19, 8.45, 2.4], [0.12, 8.45, 2.4]], "belongs_to": "3KaloR8018sAKZVwuYVbSu"}, "0td876Op155QAh5MHPRO05": {"type": "window", "global_corners": [[0.35, 13.81, 0.9], [1.35, 13.81, 0.9], [1.35, 13.88, 0.9], [0.35, 13.88, 0.9], [0.35, 13.81, 2.4], [1.35, 13.81, 2.4], [1.35, 13.88, 2.4], [0.35, 13.88, 2.4]], "belongs_to": "03hhkFXKT4RPFNu5rDrZPL"}, "0WJMcpbbzA2e6$Z5dpYikp": {"type": "window", "global_corners": [[4.75, 13.81, 0.9], [5.75, 13.81, 0.9], [5.75, 13.88, 0.9], [4.75, 13.88, 0.9], [4.75, 13.81, 2.4], [5.75, 13.81, 2.4], [5.75, 13.88, 2.4], [4.75, 13.88, 2.4]], "belongs_to": "03hhkFXKT4RPFNu5rDrZPL"}, "2zcvnUe5n40gqSh$BlyVaH": {"type": "window", "global_corners": [[3.25, 13.81, 0.9], [4.25, 13.81, 0.9], [4.25, 13.88, 0.9], [3.25, 13.88, 0.9], [3.25, 13.81, 2.4], [4.25, 13.81, 2.4], [4.25, 13.88, 2.4], [3.25, 13.88, 2.4]], "belongs_to": "03hhkFXKT4RPFNu5rDrZPL"}, "12QSop5nvChgTKqP9gJXTR": {"type": "window", "global_corners": [[1.75, 13.81, 0.9], [2.75, 13.81, 0.9], [2.75, 13.88, 0.9], [1.75, 13.88, 0.9], [1.75, 13.81, 2.4], [2.75, 13.81, 2.4], [2.75, 13.88, 2.4], [1.75, 13.88, 2.4]], "belongs_to": "03hhkFXKT4RPFNu5rDrZPL"}, "2tqQAKnbb9Puqr69a3n37D": {"type": "window", "global_corners": [[16.75, 13.81, 0.9], [17.75, 13.81, 0.9], [17.75, 13.88, 0.9], [16.75, 13.88, 0.9], [16.75, 13.81, 2.4], [17.75, 13.81, 2.4], [17.75, 13.88, 2.4], [16.75, 13.88, 2.4]], "belongs_to": "1oKaKV7Wz8IOJ10cA1PGWP"}, "1vevu6ekH25hciBayNqSbV": {"type": "window", "global_corners": [[15.25, 13.81, 0.9], [16.25, 13.81, 0.9], [16.25, 13.88, 0.9], [15.25, 13.88, 0.9], [15.25, 13.81, 2.4], [16.25, 13.81, 2.4], [16.25, 13.88, 2.4], [15.25, 13.88, 2.4]], "belongs_to": "1oKaKV7Wz8IOJ10cA1PGWP"}, "1fN0dUKvfE4x8uHeMcb2A4": {"type": "window", "global_corners": [[24.25, 13.81, 0.9], [25.25, 13.81, 0.9], [25.25, 13.88, 0.9], [24.25, 13.88, 0.9], [24.25, 13.81, 2.4], [25.25, 13.81, 2.4], [25.25, 13.88, 2.4], [24.25, 13.88, 2.4]], "belongs_to": "3j5r$vfHT3JfqUfpdRoXnP"}, "3g8MS5YmX0Zx4Mf2deNLEd": {"type": "window", "global_corners": [[25.75, 13.81, 0.9], [26.75, 13.81, 0.9], [26.75, 13.88, 0.9], [25.75, 13.88, 0.9], [25.75, 13.81, 2.4], [26.75, 13.81, 2.4], [26.75, 13.88, 2.4], [25.75, 13.88, 2.4]], "belongs_to": "3j5r$vfHT3JfqUfpdRoXnP"}, "2PhD4lAaLA3PMKnfhSTJ9q": {"type": "window", "global_corners": [[28.75, 13.81, 0.9], [29.75, 13.81, 0.9], [29.75, 13.88, 0.9], [28.75, 13.88, 0.9], [28.75, 13.81, 2.4], [29.75, 13.81, 2.4], [29.75, 13.88, 2.4], [28.75, 13.88, 2.4]], "belongs_to": "3t8qjHTuTAigDlC1x7D16b"}, "2BKSigZcT9LPO64JjoTNF4": {"type": "window", "global_corners": [[27.25, 13.81, 0.9], [28.25, 13.81, 0.9], [28.25, 13.88, 0.9], [27.25, 13.88, 0.9], [27.25, 13.81, 2.4], [28.25, 13.81, 2.4], [28.25, 13.88, 2.4], [27.25, 13.88, 2.4]], "belongs_to": "3t8qjHTuTAigDlC1x7D16b"}, "28jtanJLnD68zXO6BYmgve": {"type": "window", "global_corners": [[24.25, 2.12, 0.9], [25.25, 2.12, 0.9], [25.25, 2.19, 0.9], [24.25, 2.19, 0.9], [24.25, 2.12, 2.4], [25.25, 2.12, 2.4], [25.25, 2.19, 2.4], [24.25, 2.19, 2.4]], "belongs_to": "1DxredyET5bf_85HZe8$FO"}, "1tD8H76Wj8rwVBPPIEaOBk": {"type": "window", "global_corners": [[25.75, 2.12, 0.9], [26.75, 2.12, 0.9], [26.75, 2.19, 0.9], [25.75, 2.19, 0.9], [25.75, 2.12, 2.4], [26.75, 2.12, 2.4], [26.75, 2.19, 2.4], [25.75, 2.19, 2.4]], "belongs_to": "1DxredyET5bf_85HZe8$FO"}, "1VhUd1CGD2g8UutVlYLkue": {"type": "window", "global_corners": [[27.25, 2.12, 0.9], [28.25, 2.12, 0.9], [28.25, 2.19, 0.9], [27.25, 2.19, 0.9], [27.25, 2.12, 2.4], [28.25, 2.12, 2.4], [28.25, 2.19, 2.4], [27.25, 2.19, 2.4]], "belongs_to": "1DxredyET5bf_85HZe8$FO"}, "000vZ5hTfBgR1R0ytKrVZS": {"type": "window", "global_corners": [[28.75, 2.12, 0.9], [29.75, 2.12, 0.9], [29.75, 2.19, 0.9], [28.75, 2.19, 0.9], [28.75, 2.12, 2.4], [29.75, 2.12, 2.4], [29.75, 2.19, 2.4], [28.75, 2.19, 2.4]], "belongs_to": "1DxredyET5bf_85HZe8$FO"}, "3qlaFAAcPAeh1wBxQgEJ1O": {"type": "window", "global_corners": [[30.25, 2.12, 0.9], [31.25, 2.12, 0.9], [31.25, 2.19, 0.9], [30.25, 2.19, 0.9], [30.25, 2.12, 2.4], [31.25, 2.12, 2.4], [31.25, 2.19, 2.4], [30.25, 2.19, 2.4]], "belongs_to": "1DxredyET5bf_85HZe8$FO"}, "0uUUWyhx96pOZ1f$3c_du9": {"type": "window", "global_corners": [[31.75, 2.12, 0.9], [32.75, 2.12, 0.9], [32.75, 2.19, 0.9], [31.75, 2.19, 0.9], [31.75, 2.12, 2.4], [32.75, 2.12, 2.4], [32.75, 2.19, 2.4], [31.75, 2.19, 2.4]], "belongs_to": "1DxredyET5bf_85HZe8$FO"}, "3HAt_XvHb13AE8gYn28I5g": {"type": "window", "global_corners": [[31.75, 13.81, 0.9], [32.75, 13.81, 0.9], [32.75, 13.88, 0.9], [31.75, 13.88, 0.9], [31.75, 13.81, 2.4], [32.75, 13.81, 2.4], [32.75, 13.88, 2.4], [31.75, 13.88, 2.4]], "belongs_to": "2ED0MLfrf17BXIsuJYCs7R"}, "0$6TgsobP9PPnqNXqQeskc": {"type": "window", "global_corners": [[30.25, 13.81, 0.9], [31.25, 13.81, 0.9], [31.25, 13.88, 0.9], [30.25, 13.88, 0.9], [30.25, 13.81, 2.4], [31.25, 13.81, 2.4], [31.25, 13.88, 2.4], [30.25, 13.88, 2.4]], "belongs_to": "2ED0MLfrf17BXIsuJYCs7R"}, "0S8yN4GYfAcee_3jT9azuZ": {"type": "window", "global_corners": [[34.75, 13.81, 0.9], [35.75, 13.81, 0.9], [35.75, 13.88, 0.9], [34.75, 13.88, 0.9], [34.75, 13.81, 2.4], [35.75, 13.81, 2.4], [35.75, 13.88, 2.4], [34.75, 13.88, 2.4]], "belongs_to": "1loQAAB191MA5YmsaMJHkI"}, "2hnpR8mzTAn9yDg7byDsCY": {"type": "window", "global_corners": [[33.25, 13.81, 0.9], [34.25, 13.81, 0.9], [34.25, 13.88, 0.9], [33.25, 13.88, 0.9], [33.25, 13.81, 2.4], [34.25, 13.81, 2.4], [34.25, 13.88, 2.4], [33.25, 13.88, 2.4]], "belongs_to": "1loQAAB191MA5YmsaMJHkI"}, "2lwCvFBUz95BAyapPUrPcM": {"type": "window", "global_corners": [[37.75, 13.81, 0.9], [38.75, 13.81, 0.9], [38.75, 13.88, 0.9], [37.75, 13.88, 0.9], [37.75, 13.81, 2.4], [38.75, 13.81, 2.4], [38.75, 13.88, 2.4], [37.75, 13.88, 2.4]], "belongs_to": "3Xu6SpY4vC89stuKlMWE2n"}, "1s2ucU7sz6WPNdY1u8lvSQ": {"type": "window", "global_corners": [[36.25, 13.81, 0.9], [37.25, 13.81, 0.9], [37.25, 13.88, 0.9], [36.25, 13.88, 0.9], [36.25, 13.81, 2.4], [37.25, 13.81, 2.4], [37.25, 13.88, 2.4], [36.25, 13.88, 2.4]], "belongs_to": "3Xu6SpY4vC89stuKlMWE2n"}, "2C1mTF6lD8mgYJqKrvvqbc": {"type": "window", "global_corners": [[40.65, 13.81, 0.9], [41.65, 13.81, 0.9], [41.65, 13.88, 0.9], [40.65, 13.88, 0.9], [40.65, 13.81, 2.4], [41.65, 13.81, 2.4], [41.65, 13.88, 2.4], [40.65, 13.88, 2.4]], "belongs_to": "3yAAZZ86j388XApaG$h1X6"}, "3cBLzORtrFxwCaZldEUxGm": {"type": "window", "global_corners": [[39.25, 13.81, 0.9], [40.25, 13.81, 0.9], [40.25, 13.88, 0.9], [39.25, 13.88, 0.9], [39.25, 13.81, 2.4], [40.25, 13.81, 2.4], [40.25, 13.88, 2.4], [39.25, 13.88, 2.4]], "belongs_to": "3yAAZZ86j388XApaG$h1X6"}, "2wH9GIWt94mgMKOirAU7CY": {"type": "window", "global_corners": [[40.65, 2.12, 0.9], [41.65, 2.12, 0.9], [41.65, 2.19, 0.9], [40.65, 2.19, 0.9], [40.65, 2.12, 2.4], [41.65, 2.12, 2.4], [41.65, 2.19, 2.4], [40.65, 2.19, 2.4]], "belongs_to": "3$FatfHY1Cg9apAMwbKPN8"}, "3hUHz9q29098WsMJ20lZFe": {"type": "window", "global_corners": [[33.25, 2.12, 0.9], [34.25, 2.12, 0.9], [34.25, 2.19, 0.9], [33.25, 2.19, 0.9], [33.25, 2.12, 2.4], [34.25, 2.12, 2.4], [34.25, 2.19, 2.4], [33.25, 2.19, 2.4]], "belongs_to": "3$FatfHY1Cg9apAMwbKPN8"}, "3o$pVJjC5EqBVH2ZRwJMcp": {"type": "window", "global_corners": [[34.75, 2.12, 0.9], [35.75, 2.12, 0.9], [35.75, 2.19, 0.9], [34.75, 2.19, 0.9], [34.75, 2.12, 2.4], [35.75, 2.12, 2.4], [35.75, 2.19, 2.4], [34.75, 2.19, 2.4]], "belongs_to": "3$FatfHY1Cg9apAMwbKPN8"}, "2agthUitrEmRxrqwwPaejP": {"type": "window", "global_corners": [[36.25, 2.12, 0.9], [37.25, 2.12, 0.9], [37.25, 2.19, 0.9], [36.25, 2.19, 0.9], [36.25, 2.12, 2.4], [37.25, 2.12, 2.4], [37.25, 2.19, 2.4], [36.25, 2.19, 2.4]], "belongs_to": "3$FatfHY1Cg9apAMwbKPN8"}, "1t4Zdb3Vv8mQLPoMeqevrn": {"type": "window", "global_corners": [[37.75, 2.12, 0.9], [38.75, 2.12, 0.9], [38.75, 2.19, 0.9], [37.75, 2.19, 0.9], [37.75, 2.12, 2.4], [38.75, 2.12, 2.4], [38.75, 2.19, 2.4], [37.75, 2.19, 2.4]], "belongs_to": "3$FatfHY1Cg9apAMwbKPN8"}, "08EvXe7d51ZhzVtSteieto": {"type": "window", "global_corners": [[39.25, 2.12, 0.9], [40.25, 2.12, 0.9], [40.25, 2.19, 0.9], [39.25, 2.19, 0.9], [39.25, 2.12, 2.4], [40.25, 2.12, 2.4], [40.25, 2.19, 2.4], [39.25, 2.19, 2.4]], "belongs_to": "3$FatfHY1Cg9apAMwbKPN8"}, "0HtsZ3YcbDMwJN3vvrSgK9": {"type": "window", "global_corners": [[41.81, 7.55, 0.9], [41.88, 7.55, 0.9], [41.88, 8.45, 0.9], [41.81, 8.45, 0.9], [41.81, 7.55, 2.4], [41.88, 7.55, 2.4], [41.88, 8.45, 2.4], [41.81, 8.45, 2.4]], "belongs_to": "0_TtqXcOrDbeTXyb5q0Uxb"}, "1fPWXlbezBARmrmO_Y9jDU": {"type": "window", "global_corners": [[16.75, 2.12, 0.9], [17.75, 2.12, 0.9], [17.75, 2.19, 0.9], [16.75, 2.19, 0.9], [16.75, 2.12, 2.4], [17.75, 2.12, 2.4], [17.75, 2.19, 2.4], [16.75, 2.19, 2.4]], "belongs_to": "25QUQJ9jHAFengkpc9N7GR"}, "1Irg_U9z1CFgCoHXTaJ73y": {"type": "window", "global_corners": [[15.25, 2.12, 0.9], [16.25, 2.12, 0.9], [16.25, 2.19, 0.9], [15.25, 2.19, 0.9], [15.25, 2.12, 2.4], [16.25, 2.12, 2.4], [16.25, 2.19, 2.4], [15.25, 2.19, 2.4]], "belongs_to": "25QUQJ9jHAFengkpc9N7GR"}, "3HyKYtosrEC96fPRcfU8a1": {"type": "window", "global_corners": [[13.75, 13.81, 0.9], [14.75, 13.81, 0.9], [14.75, 13.88, 0.9], [13.75, 13.88, 0.9], [13.75, 13.81, 2.4], [14.75, 13.81, 2.4], [14.75, 13.88, 2.4], [13.75, 13.88, 2.4]], "belongs_to": "0jhU4VZ6XCxee3pjfx5VMh"}, "31WZqUkqr2U9UpIQCAkHVB": {"type": "window", "global_corners": [[12.25, 13.81, 0.9], [13.25, 13.81, 0.9], [13.25, 13.88, 0.9], [12.25, 13.88, 0.9], [12.25, 13.81, 2.4], [13.25, 13.81, 2.4], [13.25, 13.88, 2.4], [12.25, 13.88, 2.4]], "belongs_to": "0jhU4VZ6XCxee3pjfx5VMh"}, "27$3O5O5r4zP4FJdp1zwdN": {"type": "window", "global_corners": [[10.75, 13.81, 0.9], [11.75, 13.81, 0.9], [11.75, 13.88, 0.9], [10.75, 13.88, 0.9], [10.75, 13.81, 2.4], [11.75, 13.81, 2.4], [11.75, 13.88, 2.4], [10.75, 13.88, 2.4]], "belongs_to": "0jhU4VZ6XCxee3pjfx5VMh"}, "0pPpDUymrBF8Wc$W7Gv4T$": {"type": "window", "global_corners": [[9.25, 13.81, 0.9], [10.25, 13.81, 0.9], [10.25, 13.88, 0.9], [9.25, 13.88, 0.9], [9.25, 13.81, 2.4], [10.25, 13.81, 2.4], [10.25, 13.88, 2.4], [9.25, 13.88, 2.4]], "belongs_to": "0jhU4VZ6XCxee3pjfx5VMh"}, "3cjmnELbT4ZgU434Wpw8$2": {"type": "window", "global_corners": [[7.75, 13.81, 0.9], [8.75, 13.81, 0.9], [8.75, 13.88, 0.9], [7.75, 13.88, 0.9], [7.75, 13.81, 2.4], [8.75, 13.81, 2.4], [8.75, 13.88, 2.4], [7.75, 13.88, 2.4]], "belongs_to": "0jhU4VZ6XCxee3pjfx5VMh"}, "1KKnvDZrr6qPZi0fbRfk_i": {"type": "window", "global_corners": [[6.25, 13.81, 0.9], [7.25, 13.81, 0.9], [7.25, 13.88, 0.9], [6.25, 13.88, 0.9], [6.25, 13.81, 2.4], [7.25, 13.81, 2.4], [7.25, 13.88, 2.4], [6.25, 13.88, 2.4]], "belongs_to": "0jhU4VZ6XCxee3pjfx5VMh"}, "2S05fJwurB0AsobKzEqBs1": {"type": "window", "global_corners": [[23.81, 0.55, 0.1], [23.89, 0.55, 0.1], [23.89, 1.45, 0.1], [23.81, 1.45, 0.1], [23.81, 0.55, 2.1], [23.89, 0.55, 2.1], [23.89, 1.45, 2.1], [23.81, 1.45, 2.1]], "belongs_to": "1RP4kkhTDFJuLugWfrM_1s"}, "2UjUodKnf77PmcAVpITSgL": {"type": "window", "global_corners": [[22.55, 0.12, 0.1], [23.45, 0.12, 0.1], [23.45, 0.19, 0.1], [22.55, 0.19, 0.1], [22.55, 0.12, 2.1], [23.45, 0.12, 2.1], [23.45, 0.19, 2.1], [22.55, 0.19, 2.1]], "belongs_to": "1RP4kkhTDFJuLugWfrM_1s"}, "0KqFIy5jL1Mgh2ggQ4WLch": {"type": "window", "global_corners": [[18.5, 0.12, 0.1], [19.5, 0.12, 0.1], [19.5, 0.19, 0.1], [18.5, 0.19, 0.1], [18.5, 0.12, 2.1], [19.5, 0.12, 2.1], [19.5, 0.19, 2.1], [18.5, 0.19, 2.1]], "belongs_to": "1RP4kkhTDFJuLugWfrM_1s"}, "12ErTRo_9EmBI9cF9PJCvF": {"type": "window", "global_corners": [[18.11, 0.55, 0.1], [18.19, 0.55, 0.1], [18.19, 1.45, 0.1], [18.11, 1.45, 0.1], [18.11, 0.55, 2.1], [18.19, 0.55, 2.1], [18.19, 1.45, 2.1], [18.11, 1.45, 2.1]], "belongs_to": "1RP4kkhTDFJuLugWfrM_1s"}, "1II2wI2iz2xugPBtxLqfRA": {"type": "window", "global_corners": [[0.12, 7.55, 3.9], [0.19, 7.55, 3.9], [0.19, 8.45, 3.9], [0.12, 8.45, 3.9], [0.12, 7.55, 5.4], [0.19, 7.55, 5.4], [0.19, 8.45, 5.4], [0.12, 8.45, 5.4]], "belongs_to": "25CC32yK130ALlKsnej9JW"}, "3yGeEHOp97MPf7P0QPdQGT": {"type": "window", "global_corners": [[16.75, 13.81, 3.9], [17.75, 13.81, 3.9], [17.75, 13.88, 3.9], [16.75, 13.88, 3.9], [16.75, 13.81, 5.4], [17.75, 13.81, 5.4], [17.75, 13.88, 5.4], [16.75, 13.88, 5.4]], "belongs_to": "37pP75EaP1axQNg3rWc_WT"}, "2CnQ7ixwv8A9Jwtk_6wiBp": {"type": "window", "global_corners": [[15.25, 13.81, 3.9], [16.25, 13.81, 3.9], [16.25, 13.88, 3.9], [15.25, 13.88, 3.9], [15.25, 13.81, 5.4], [16.25, 13.81, 5.4], [16.25, 13.88, 5.4], [15.25, 13.88, 5.4]], "belongs_to": "37pP75EaP1axQNg3rWc_WT"}, "3jPBVBqyH6RgTDfklWLj5B": {"type": "window", "global_corners": [[24.25, 13.81, 3.9], [25.25, 13.81, 3.9], [25.25, 13.88, 3.9], [24.25, 13.88, 3.9], [24.25, 13.81, 5.4], [25.25, 13.81, 5.4], [25.25, 13.88, 5.4], [24.25, 13.88, 5.4]], "belongs_to": "0f6kjO4cnBngLgZgtaoBTE"}, "09nsmlIP1Av8Gqo7k1gGXA": {"type": "window", "global_corners": [[25.75, 13.81, 3.9], [26.75, 13.81, 3.9], [26.75, 13.88, 3.9], [25.75, 13.88, 3.9], [25.75, 13.81, 5.4], [26.75, 13.81, 5.4], [26.75, 13.88, 5.4], [25.75, 13.88, 5.4]], "belongs_to": "0f6kjO4cnBngLgZgtaoBTE"}, "2kyp5olOX6YxfL8$tctAgH": {"type": "window", "global_corners": [[41.81, 7.55, 3.9], [41.88, 7.55, 3.9], [41.88, 8.45, 3.9], [41.81, 8.45, 3.9], [41.81, 7.55, 5.4], [41.88, 7.55, 5.4], [41.88, 8.45, 5.4], [41.81, 8.45, 5.4]], "belongs_to": "3XJSZHVdLFTQTPYNfhA6a2"}, "2TM3hOfDLEKgLHIoi2G2eE": {"type": "window", "global_corners": [[31.75, 13.81, 3.9], [32.75, 13.81, 3.9], [32.75, 13.88, 3.9], [31.75, 13.88, 3.9], [31.75, 13.81, 5.4], [32.75, 13.81, 5.4], [32.75, 13.88, 5.4], [31.75, 13.88, 5.4]], "belongs_to": "1AW8GAtUnEYB9XPWOUYKK5"}, "3TaVJS_WrFjvF4FNvIpjkU": {"type": "window", "global_corners": [[30.25, 13.81, 3.9], [31.25, 13.81, 3.9], [31.25, 13.88, 3.9], [30.25, 13.88, 3.9], [30.25, 13.81, 5.4], [31.25, 13.81, 5.4], [31.25, 13.88, 5.4], [30.25, 13.88, 5.4]], "belongs_to": "1AW8GAtUnEYB9XPWOUYKK5"}, "2sPrxFKUnDQBesnyFyTX7C": {"type": "window", "global_corners": [[40.65, 2.12, 3.9], [41.65, 2.12, 3.9], [41.65, 2.19, 3.9], [40.65, 2.19, 3.9], [40.65, 2.12, 5.4], [41.65, 2.12, 5.4], [41.65, 2.19, 5.4], [40.65, 2.19, 5.4]], "belongs_to": "24vVAUYDH2SetutQQsZBMv"}, "3k8ejU_PjCWBuPFpm1k2lH": {"type": "window", "global_corners": [[39.25, 2.12, 3.9], [40.25, 2.12, 3.9], [40.25, 2.19, 3.9], [39.25, 2.19, 3.9], [39.25, 2.12, 5.4], [40.25, 2.12, 5.4], [40.25, 2.19, 5.4], [39.25, 2.19, 5.4]], "belongs_to": "24vVAUYDH2SetutQQsZBMv"}, "1OLRx1anXAohtkhV733dGP": {"type": "window", "global_corners": [[37.75, 2.12, 3.9], [38.75, 2.12, 3.9], [38.75, 2.19, 3.9], [37.75, 2.19, 3.9], [37.75, 2.12, 5.4], [38.75, 2.12, 5.4], [38.75, 2.19, 5.4], [37.75, 2.19, 5.4]], "belongs_to": "24vVAUYDH2SetutQQsZBMv"}, "1mUlkaN4jFkfHh1zNVHhGj": {"type": "window", "global_corners": [[36.25, 2.12, 3.9], [37.25, 2.12, 3.9], [37.25, 2.19, 3.9], [36.25, 2.19, 3.9], [36.25, 2.12, 5.4], [37.25, 2.12, 5.4], [37.25, 2.19, 5.4], [36.25, 2.19, 5.4]], "belongs_to": "24vVAUYDH2SetutQQsZBMv"}, "1z0qMKUIT5IxhyyHbF4ocp": {"type": "window", "global_corners": [[34.75, 2.12, 3.9], [35.75, 2.12, 3.9], [35.75, 2.19, 3.9], [34.75, 2.19, 3.9], [34.75, 2.12, 5.4], [35.75, 2.12, 5.4], [35.75, 2.19, 5.4], [34.75, 2.19, 5.4]], "belongs_to": "24vVAUYDH2SetutQQsZBMv"}, "39pRQ$7l15fOjHNjfl3enL": {"type": "window", "global_corners": [[33.25, 2.12, 3.9], [34.25, 2.12, 3.9], [34.25, 2.19, 3.9], [33.25, 2.19, 3.9], [33.25, 2.12, 5.4], [34.25, 2.12, 5.4], [34.25, 2.19, 5.4], [33.25, 2.19, 5.4]], "belongs_to": "24vVAUYDH2SetutQQsZBMv"}, "3jVh8jSJrDvA6MPkB86x3V": {"type": "window", "global_corners": [[31.75, 2.12, 3.9], [32.75, 2.12, 3.9], [32.75, 2.19, 3.9], [31.75, 2.19, 3.9], [31.75, 2.12, 5.4], [32.75, 2.12, 5.4], [32.75, 2.19, 5.4], [31.75, 2.19, 5.4]], "belongs_to": "2goaA6RR92B9xducYbaQVU"}, "2S3C3uY4L3E8GfjjcpTjpF": {"type": "window", "global_corners": [[30.25, 2.12, 3.9], [31.25, 2.12, 3.9], [31.25, 2.19, 3.9], [30.25, 2.19, 3.9], [30.25, 2.12, 5.4], [31.25, 2.12, 5.4], [31.25, 2.19, 5.4], [30.25, 2.19, 5.4]], "belongs_to": "2goaA6RR92B9xducYbaQVU"}, "0JtLRXJlvE_wC5_4sLnvdj": {"type": "window", "global_corners": [[28.75, 2.12, 3.9], [29.75, 2.12, 3.9], [29.75, 2.19, 3.9], [28.75, 2.19, 3.9], [28.75, 2.12, 5.4], [29.75, 2.12, 5.4], [29.75, 2.19, 5.4], [28.75, 2.19, 5.4]], "belongs_to": "2goaA6RR92B9xducYbaQVU"}, "3UZtqiBsz5uvWB4kZmuS1Q": {"type": "window", "global_corners": [[27.25, 2.12, 3.9], [28.25, 2.12, 3.9], [28.25, 2.19, 3.9], [27.25, 2.19, 3.9], [27.25, 2.12, 5.4], [28.25, 2.12, 5.4], [28.25, 2.19, 5.4], [27.25, 2.19, 5.4]], "belongs_to": "2goaA6RR92B9xducYbaQVU"}, "1_H_m5RiH9X8BR$Fz7YY7j": {"type": "window", "global_corners": [[34.75, 13.81, 3.9], [35.75, 13.81, 3.9], [35.75, 13.88, 3.9], [34.75, 13.88, 3.9], [34.75, 13.81, 5.4], [35.75, 13.81, 5.4], [35.75, 13.88, 5.4], [34.75, 13.88, 5.4]], "belongs_to": "0i4GPkF$j1$P1_N4yoKfHm"}, "31vL2xKtv6b8xITngnOCX4": {"type": "window", "global_corners": [[33.25, 13.81, 3.9], [34.25, 13.81, 3.9], [34.25, 13.88, 3.9], [33.25, 13.88, 3.9], [33.25, 13.81, 5.4], [34.25, 13.81, 5.4], [34.25, 13.88, 5.4], [33.25, 13.88, 5.4]], "belongs_to": "0i4GPkF$j1$P1_N4yoKfHm"}, "34z_sfy5r7MxZO_XK2tdyk": {"type": "window", "global_corners": [[0.35, 13.81, 3.9], [1.35, 13.81, 3.9], [1.35, 13.88, 3.9], [0.35, 13.88, 3.9], [0.35, 13.81, 5.4], [1.35, 13.81, 5.4], [1.35, 13.88, 5.4], [0.35, 13.88, 5.4]], "belongs_to": "2Yd3UbuHLF0P7Q5pq$wqrF"}, "03SJ_6GzL72BUsuqP6BUv3": {"type": "window", "global_corners": [[1.75, 13.81, 3.9], [2.75, 13.81, 3.9], [2.75, 13.88, 3.9], [1.75, 13.88, 3.9], [1.75, 13.81, 5.4], [2.75, 13.81, 5.4], [2.75, 13.88, 5.4], [1.75, 13.88, 5.4]], "belongs_to": "2Yd3UbuHLF0P7Q5pq$wqrF"}, "3zXYrOG$5AIAmg3jOwc8e1": {"type": "window", "global_corners": [[4.75, 13.81, 3.9], [5.75, 13.81, 3.9], [5.75, 13.88, 3.9], [4.75, 13.88, 3.9], [4.75, 13.81, 5.4], [5.75, 13.81, 5.4], [5.75, 13.88, 5.4], [4.75, 13.88, 5.4]], "belongs_to": "1GtYUXG753_h6i4vKAf46v"}, "2FhF5ftpfAoR5u9P0zRDN2": {"type": "window", "global_corners": [[3.25, 13.81, 3.9], [4.25, 13.81, 3.9], [4.25, 13.88, 3.9], [3.25, 13.88, 3.9], [3.25, 13.81, 5.4], [4.25, 13.81, 5.4], [4.25, 13.88, 5.4], [3.25, 13.88, 5.4]], "belongs_to": "1GtYUXG753_h6i4vKAf46v"}, "1pPdANFrDBBhYWYhTHEEHn": {"type": "window", "global_corners": [[7.75, 13.81, 3.9], [8.75, 13.81, 3.9], [8.75, 13.88, 3.9], [7.75, 13.88, 3.9], [7.75, 13.81, 5.4], [8.75, 13.81, 5.4], [8.75, 13.88, 5.4], [7.75, 13.88, 5.4]], "belongs_to": "0VWZeARNT8IAUcPL5OoYiA"}, "1CC7dXY6v5nAdc$PmuzWuu": {"type": "window", "global_corners": [[6.25, 13.81, 3.9], [7.25, 13.81, 3.9], [7.25, 13.88, 3.9], [6.25, 13.88, 3.9], [6.25, 13.81, 5.4], [7.25, 13.81, 5.4], [7.25, 13.88, 5.4], [6.25, 13.88, 5.4]], "belongs_to": "0VWZeARNT8IAUcPL5OoYiA"}, "22eq1cKyX4ORpHxEO$xo4v": {"type": "window", "global_corners": [[13.75, 13.81, 3.9], [14.75, 13.81, 3.9], [14.75, 13.88, 3.9], [13.75, 13.88, 3.9], [13.75, 13.81, 5.4], [14.75, 13.81, 5.4], [14.75, 13.88, 5.4], [13.75, 13.88, 5.4]], "belongs_to": "3kV3mGMIX3BvUw5dL_lJVg"}, "3f8gKg5kT30h_8UXOmLt72": {"type": "window", "global_corners": [[12.25, 13.81, 3.9], [13.25, 13.81, 3.9], [13.25, 13.88, 3.9], [12.25, 13.88, 3.9], [12.25, 13.81, 5.4], [13.25, 13.81, 5.4], [13.25, 13.88, 5.4], [12.25, 13.88, 5.4]], "belongs_to": "3kV3mGMIX3BvUw5dL_lJVg"}, "3panYjerbCSQl08K8o34mj": {"type": "window", "global_corners": [[22.75, 2.12, 3.9], [23.75, 2.12, 3.9], [23.75, 2.19, 3.9], [22.75, 2.19, 3.9], [22.75, 2.12, 5.4], [23.75, 2.12, 5.4], [23.75, 2.19, 5.4], [22.75, 2.19, 5.4]], "belongs_to": "1yZQvqj15Ab8eMXDuz85Dy"}, "2LkcdSrN1BN9bjMXtrVXB5": {"type": "window", "global_corners": [[21.25, 2.12, 3.9], [22.25, 2.12, 3.9], [22.25, 2.19, 3.9], [21.25, 2.19, 3.9], [21.25, 2.12, 5.4], [22.25, 2.12, 5.4], [22.25, 2.19, 5.4], [21.25, 2.19, 5.4]], "belongs_to": "1yZQvqj15Ab8eMXDuz85Dy"}, "0NwAXV3355GR00was0Pjhg": {"type": "window", "global_corners": [[19.75, 2.12, 3.9], [20.75, 2.12, 3.9], [20.75, 2.19, 3.9], [19.75, 2.19, 3.9], [19.75, 2.12, 5.4], [20.75, 2.12, 5.4], [20.75, 2.19, 5.4], [19.75, 2.19, 5.4]], "belongs_to": "1yZQvqj15Ab8eMXDuz85Dy"}, "2JMzFDlyLC_vpXgeQ4GDNH": {"type": "window", "global_corners": [[18.25, 2.12, 3.9], [19.25, 2.12, 3.9], [19.25, 2.19, 3.9], [18.25, 2.19, 3.9], [18.25, 2.12, 5.4], [19.25, 2.12, 5.4], [19.25, 2.19, 5.4], [18.25, 2.19, 5.4]], "belongs_to": "1yZQvqj15Ab8eMXDuz85Dy"}, "0m$kvDvUr77f4o9JMw6ppP": {"type": "window", "global_corners": [[0.35, 2.12, 3.9], [1.35, 2.12, 3.9], [1.35, 2.19, 3.9], [0.35, 2.19, 3.9], [0.35, 2.12, 5.4], [1.35, 2.12, 5.4], [1.35, 2.19, 5.4], [0.35, 2.19, 5.4]], "belongs_to": "0uC7OD3$5F7v$zL3aaoEig"}, "2c8tkvv0f3bx0r2cE2KbR4": {"type": "window", "global_corners": [[4.75, 2.12, 3.9], [5.75, 2.12, 3.9], [5.75, 2.19, 3.9], [4.75, 2.19, 3.9], [4.75, 2.12, 5.4], [5.75, 2.12, 5.4], [5.75, 2.19, 5.4], [4.75, 2.19, 5.4]], "belongs_to": "0uC7OD3$5F7v$zL3aaoEig"}, "07j7ld5m1AKfwXwsD8BKk6": {"type": "window", "global_corners": [[3.25, 2.12, 3.9], [4.25, 2.12, 3.9], [4.25, 2.19, 3.9], [3.25, 2.19, 3.9], [3.25, 2.12, 5.4], [4.25, 2.12, 5.4], [4.25, 2.19, 5.4], [3.25, 2.19, 5.4]], "belongs_to": "0uC7OD3$5F7v$zL3aaoEig"}, "2PyPcf7HvDGQxPopRGPDKI": {"type": "window", "global_corners": [[1.75, 2.12, 3.9], [2.75, 2.12, 3.9], [2.75, 2.19, 3.9], [1.75, 2.19, 3.9], [1.75, 2.12, 5.4], [2.75, 2.12, 5.4], [2.75, 2.19, 5.4], [1.75, 2.19, 5.4]], "belongs_to": "0uC7OD3$5F7v$zL3aaoEig"}, "0vzBs_8_n40xRpBtuEXQlk": {"type": "window", "global_corners": [[40.65, 13.81, 3.9], [41.65, 13.81, 3.9], [41.65, 13.88, 3.9], [40.65, 13.88, 3.9], [40.65, 13.81, 5.4], [41.65, 13.81, 5.4], [41.65, 13.88, 5.4], [40.65, 13.88, 5.4]], "belongs_to": "2E2TaOnqD0chpbuH8tXCpW"}, "2q$7ICGvL3zvLmzSLHMQRS": {"type": "window", "global_corners": [[39.25, 13.81, 3.9], [40.25, 13.81, 3.9], [40.25, 13.88, 3.9], [39.25, 13.88, 3.9], [39.25, 13.81, 5.4], [40.25, 13.81, 5.4], [40.25, 13.88, 5.4], [39.25, 13.88, 5.4]], "belongs_to": "2E2TaOnqD0chpbuH8tXCpW"}, "0L1ke1dG93fxxhtLVwOTsT": {"type": "window", "global_corners": [[10.75, 2.12, 3.9], [11.75, 2.12, 3.9], [11.75, 2.19, 3.9], [10.75, 2.19, 3.9], [10.75, 2.12, 5.4], [11.75, 2.12, 5.4], [11.75, 2.19, 5.4], [10.75, 2.19, 5.4]], "belongs_to": "3shuyF_Yb7yu2P$QLB2s8G"}, "2muLeR9tf5FfEKGfOAn8sb": {"type": "window", "global_corners": [[9.25, 2.12, 3.9], [10.25, 2.12, 3.9], [10.25, 2.19, 3.9], [9.25, 2.19, 3.9], [9.25, 2.12, 5.4], [10.25, 2.12, 5.4], [10.25, 2.19, 5.4], [9.25, 2.19, 5.4]], "belongs_to": "3shuyF_Yb7yu2P$QLB2s8G"}, "0AlQO9vJD8yQs$jjO$RhN4": {"type": "window", "global_corners": [[7.75, 2.12, 3.9], [8.75, 2.12, 3.9], [8.75, 2.19, 3.9], [7.75, 2.19, 3.9], [7.75, 2.12, 5.4], [8.75, 2.12, 5.4], [8.75, 2.19, 5.4], [7.75, 2.19, 5.4]], "belongs_to": "3shuyF_Yb7yu2P$QLB2s8G"}, "14tRml$oP0Rhmg9zCpGzdf": {"type": "window", "global_corners": [[6.25, 2.12, 3.9], [7.25, 2.12, 3.9], [7.25, 2.19, 3.9], [6.25, 2.19, 3.9], [6.25, 2.12, 5.4], [7.25, 2.12, 5.4], [7.25, 2.19, 5.4], [6.25, 2.19, 5.4]], "belongs_to": "3shuyF_Yb7yu2P$QLB2s8G"}, "1bxtpaVk912hlBqFs8DpVp": {"type": "window", "global_corners": [[16.75, 2.12, 3.9], [17.75, 2.12, 3.9], [17.75, 2.19, 3.9], [16.75, 2.19, 3.9], [16.75, 2.12, 5.4], [17.75, 2.12, 5.4], [17.75, 2.19, 5.4], [16.75, 2.19, 5.4]], "belongs_to": "0UiHARbFzF1RT4g_GKem_B"}, "1pEJsF8kH4BQ$w9DVNUS8V": {"type": "window", "global_corners": [[15.25, 2.12, 3.9], [16.25, 2.12, 3.9], [16.25, 2.19, 3.9], [15.25, 2.19, 3.9], [15.25, 2.12, 5.4], [16.25, 2.12, 5.4], [16.25, 2.19, 5.4], [15.25, 2.19, 5.4]], "belongs_to": "0UiHARbFzF1RT4g_GKem_B"}, "3ZvIiAd7b8tvll14FCaSxA": {"type": "window", "global_corners": [[13.75, 2.12, 3.9], [14.75, 2.12, 3.9], [14.75, 2.19, 3.9], [13.75, 2.19, 3.9], [13.75, 2.12, 5.4], [14.75, 2.12, 5.4], [14.75, 2.19, 5.4], [13.75, 2.19, 5.4]], "belongs_to": "0UiHARbFzF1RT4g_GKem_B"}, "3LxPgFi8zB9O2dL$OVvll8": {"type": "window", "global_corners": [[12.25, 2.12, 3.9], [13.25, 2.12, 3.9], [13.25, 2.19, 3.9], [12.25, 2.19, 3.9], [12.25, 2.12, 5.4], [13.25, 2.12, 5.4], [13.25, 2.19, 5.4], [12.25, 2.19, 5.4]], "belongs_to": "0UiHARbFzF1RT4g_GKem_B"}, "2iLTU_LYz3NA91FzuoqriL": {"type": "window", "global_corners": [[37.75, 13.81, 3.9], [38.75, 13.81, 3.9], [38.75, 13.88, 3.9], [37.75, 13.88, 3.9], [37.75, 13.81, 5.4], [38.75, 13.81, 5.4], [38.75, 13.88, 5.4], [37.75, 13.88, 5.4]], "belongs_to": "1LVv$xQpj6k8KE6pcNlDDU"}, "30S9Awv3LEe8VCVTEwi68n": {"type": "window", "global_corners": [[36.25, 13.81, 3.9], [37.25, 13.81, 3.9], [37.25, 13.88, 3.9], [36.25, 13.88, 3.9], [36.25, 13.81, 5.4], [37.25, 13.81, 5.4], [37.25, 13.88, 5.4], [36.25, 13.88, 5.4]], "belongs_to": "1LVv$xQpj6k8KE6pcNlDDU"}, "14lr70JTX5Zw5AEQUrJRI6": {"type": "window", "global_corners": [[28.75, 13.81, 3.9], [29.75, 13.81, 3.9], [29.75, 13.88, 3.9], [28.75, 13.88, 3.9], [28.75, 13.81, 5.4], [29.75, 13.81, 5.4], [29.75, 13.88, 5.4], [28.75, 13.88, 5.4]], "belongs_to": "1a3ixYyUn0QO4HWUYKN$4p"}, "1woJxRP9rBzA0NGvvq6Jbs": {"type": "window", "global_corners": [[27.25, 13.81, 3.9], [28.25, 13.81, 3.9], [28.25, 13.88, 3.9], [27.25, 13.88, 3.9], [27.25, 13.81, 5.4], [28.25, 13.81, 5.4], [28.25, 13.88, 5.4], [27.25, 13.88, 5.4]], "belongs_to": "1a3ixYyUn0QO4HWUYKN$4p"}, "1mxN55cZPF6hKlsvawmd2i": {"type": "window", "global_corners": [[25.75, 2.12, 3.9], [26.75, 2.12, 3.9], [26.75, 2.19, 3.9], [25.75, 2.19, 3.9], [25.75, 2.12, 5.4], [26.75, 2.12, 5.4], [26.75, 2.19, 5.4], [25.75, 2.19, 5.4]], "belongs_to": "3iSzpa9d93jhTDB7hG0QBW"}, "3fUog30lP6pwOTrTR2sk8d": {"type": "window", "global_corners": [[24.25, 2.12, 3.9], [25.25, 2.12, 3.9], [25.25, 2.19, 3.9], [24.25, 2.19, 3.9], [24.25, 2.12, 5.4], [25.25, 2.12, 5.4], [25.25, 2.19, 5.4], [24.25, 2.19, 5.4]], "belongs_to": "3iSzpa9d93jhTDB7hG0QBW"}, "2vthESqkPCtexTHr1MwOxj": {"type": "window", "global_corners": [[10.75, 13.81, 3.9], [11.75, 13.81, 3.9], [11.75, 13.88, 3.9], [10.75, 13.88, 3.9], [10.75, 13.81, 5.4], [11.75, 13.81, 5.4], [11.75, 13.88, 5.4], [10.75, 13.88, 5.4]], "belongs_to": "0K6ICBa1zCjvUnsy8qMIRC"}, "2636AictfCaBavk86H6D4D": {"type": "window", "global_corners": [[9.25, 13.81, 3.9], [10.25, 13.81, 3.9], [10.25, 13.88, 3.9], [9.25, 13.88, 3.9], [9.25, 13.81, 5.4], [10.25, 13.81, 5.4], [10.25, 13.88, 5.4], [9.25, 13.88, 5.4]], "belongs_to": "0K6ICBa1zCjvUnsy8qMIRC"}, "2zTK8GIWP5CPRPLmzfTLA_": {"type": "window", "global_corners": [[24.25, 13.81, 6.9], [25.25, 13.81, 6.9], [25.25, 13.88, 6.9], [24.25, 13.88, 6.9], [24.25, 13.81, 8.4], [25.25, 13.81, 8.4], [25.25, 13.88, 8.4], [24.25, 13.88, 8.4]], "belongs_to": "3M3dydUxH2hR7Uvg9QNhS$"}, "2ne1IcZdrDPRb$8OCHUml1": {"type": "window", "global_corners": [[25.75, 13.81, 6.9], [26.75, 13.81, 6.9], [26.75, 13.88, 6.9], [25.75, 13.88, 6.9], [25.75, 13.81, 8.4], [26.75, 13.81, 8.4], [26.75, 13.88, 8.4], [25.75, 13.88, 8.4]], "belongs_to": "3M3dydUxH2hR7Uvg9QNhS$"}, "3XWJoOAe95r84KuBtu9JdR": {"type": "window", "global_corners": [[10.75, 2.12, 6.9], [11.75, 2.12, 6.9], [11.75, 2.19, 6.9], [10.75, 2.19, 6.9], [10.75, 2.12, 8.4], [11.75, 2.12, 8.4], [11.75, 2.19, 8.4], [10.75, 2.19, 8.4]], "belongs_to": "2lebmw3XD9w9PIIn4HKbwh"}, "2wzUmDh8LD9BcIe4cEFuli": {"type": "window", "global_corners": [[9.25, 2.12, 6.9], [10.25, 2.12, 6.9], [10.25, 2.19, 6.9], [9.25, 2.19, 6.9], [9.25, 2.12, 8.4], [10.25, 2.12, 8.4], [10.25, 2.19, 8.4], [9.25, 2.19, 8.4]], "belongs_to": "2lebmw3XD9w9PIIn4HKbwh"}, "2dUUX5v1j6ofLpFT0PekPV": {"type": "window", "global_corners": [[7.75, 2.12, 6.9], [8.75, 2.12, 6.9], [8.75, 2.19, 6.9], [7.75, 2.19, 6.9], [7.75, 2.12, 8.4], [8.75, 2.12, 8.4], [8.75, 2.19, 8.4], [7.75, 2.19, 8.4]], "belongs_to": "2lebmw3XD9w9PIIn4HKbwh"}, "28pY$eTgz34vpE27jGTytk": {"type": "window", "global_corners": [[6.25, 2.12, 6.9], [7.25, 2.12, 6.9], [7.25, 2.19, 6.9], [6.25, 2.19, 6.9], [6.25, 2.12, 8.4], [7.25, 2.12, 8.4], [7.25, 2.19, 8.4], [6.25, 2.19, 8.4]], "belongs_to": "2lebmw3XD9w9PIIn4HKbwh"}, "1lclf89IDDS8I01Hi8Sb8Z": {"type": "window", "global_corners": [[16.75, 2.12, 6.9], [17.75, 2.12, 6.9], [17.75, 2.19, 6.9], [16.75, 2.19, 6.9], [16.75, 2.12, 8.4], [17.75, 2.12, 8.4], [17.75, 2.19, 8.4], [16.75, 2.19, 8.4]], "belongs_to": "09m2tgyfr9UfikvrKFMkeD"}, "0J1SwSeib5NelMocEXw8uQ": {"type": "window", "global_corners": [[15.25, 2.12, 6.9], [16.25, 2.12, 6.9], [16.25, 2.19, 6.9], [15.25, 2.19, 6.9], [15.25, 2.12, 8.4], [16.25, 2.12, 8.4], [16.25, 2.19, 8.4], [15.25, 2.19, 8.4]], "belongs_to": "09m2tgyfr9UfikvrKFMkeD"}, "1xlLX8Zrj9wAZCni6ROM5N": {"type": "window", "global_corners": [[13.75, 2.12, 6.9], [14.75, 2.12, 6.9], [14.75, 2.19, 6.9], [13.75, 2.19, 6.9], [13.75, 2.12, 8.4], [14.75, 2.12, 8.4], [14.75, 2.19, 8.4], [13.75, 2.19, 8.4]], "belongs_to": "09m2tgyfr9UfikvrKFMkeD"}, "16PPPa8vv5HuPkSmln13OV": {"type": "window", "global_corners": [[12.25, 2.12, 6.9], [13.25, 2.12, 6.9], [13.25, 2.19, 6.9], [12.25, 2.19, 6.9], [12.25, 2.12, 8.4], [13.25, 2.12, 8.4], [13.25, 2.19, 8.4], [12.25, 2.19, 8.4]], "belongs_to": "09m2tgyfr9UfikvrKFMkeD"}, "13abvHCs97gOGS1VyTZ36D": {"type": "window", "global_corners": [[22.75, 2.12, 6.9], [23.75, 2.12, 6.9], [23.75, 2.19, 6.9], [22.75, 2.19, 6.9], [22.75, 2.12, 8.4], [23.75, 2.12, 8.4], [23.75, 2.19, 8.4], [22.75, 2.19, 8.4]], "belongs_to": "0dc6ovxJLDww6sjSpu_cfN"}, "3f7Fz2Ssb9qBEvcT1P5nR5": {"type": "window", "global_corners": [[21.25, 2.12, 6.9], [22.25, 2.12, 6.9], [22.25, 2.19, 6.9], [21.25, 2.19, 6.9], [21.25, 2.12, 8.4], [22.25, 2.12, 8.4], [22.25, 2.19, 8.4], [21.25, 2.19, 8.4]], "belongs_to": "0dc6ovxJLDww6sjSpu_cfN"}, "0r2Ds1$6P2DwQ4MwKwJura": {"type": "window", "global_corners": [[19.75, 2.12, 6.9], [20.75, 2.12, 6.9], [20.75, 2.19, 6.9], [19.75, 2.19, 6.9], [19.75, 2.12, 8.4], [20.75, 2.12, 8.4], [20.75, 2.19, 8.4], [19.75, 2.19, 8.4]], "belongs_to": "0dc6ovxJLDww6sjSpu_cfN"}, "0QgcTUhxfBlRUTxmdrocfw": {"type": "window", "global_corners": [[18.25, 2.12, 6.9], [19.25, 2.12, 6.9], [19.25, 2.19, 6.9], [18.25, 2.19, 6.9], [18.25, 2.12, 8.4], [19.25, 2.12, 8.4], [19.25, 2.19, 8.4], [18.25, 2.19, 8.4]], "belongs_to": "0dc6ovxJLDww6sjSpu_cfN"}, "0lSCVI_pz9aRsLneS8b7BY": {"type": "window", "global_corners": [[28.75, 2.12, 6.9], [29.75, 2.12, 6.9], [29.75, 2.19, 6.9], [28.75, 2.19, 6.9], [28.75, 2.12, 8.4], [29.75, 2.12, 8.4], [29.75, 2.19, 8.4], [28.75, 2.19, 8.4]], "belongs_to": "0U5AcnRYX7aw$OIZXqMUaR"}, "0yxjkv3wvEtQPAWliouV$u": {"type": "window", "global_corners": [[27.25, 2.12, 6.9], [28.25, 2.12, 6.9], [28.25, 2.19, 6.9], [27.25, 2.19, 6.9], [27.25, 2.12, 8.4], [28.25, 2.12, 8.4], [28.25, 2.19, 8.4], [27.25, 2.19, 8.4]], "belongs_to": "0U5AcnRYX7aw$OIZXqMUaR"}, "22mYo$ZgTCP90ywROIM98L": {"type": "window", "global_corners": [[25.75, 2.12, 6.9], [26.75, 2.12, 6.9], [26.75, 2.19, 6.9], [25.75, 2.19, 6.9], [25.75, 2.12, 8.4], [26.75, 2.12, 8.4], [26.75, 2.19, 8.4], [25.75, 2.19, 8.4]], "belongs_to": "0U5AcnRYX7aw$OIZXqMUaR"}, "3FhKOKIeb8QOyMFfTkmffU": {"type": "window", "global_corners": [[24.25, 2.12, 6.9], [25.25, 2.12, 6.9], [25.25, 2.19, 6.9], [24.25, 2.19, 6.9], [24.25, 2.12, 8.4], [25.25, 2.12, 8.4], [25.25, 2.19, 8.4], [24.25, 2.19, 8.4]], "belongs_to": "0U5AcnRYX7aw$OIZXqMUaR"}, "2gtoeoCt9CBhiwfjH_Yl8E": {"type": "window", "global_corners": [[4.75, 13.81, 6.9], [5.75, 13.81, 6.9], [5.75, 13.88, 6.9], [4.75, 13.88, 6.9], [4.75, 13.81, 8.4], [5.75, 13.81, 8.4], [5.75, 13.88, 8.4], [4.75, 13.88, 8.4]], "belongs_to": "1jJ7opRcX6uevup8Hnq0$2"}, "1xD7nIclXAbe0AcpTv8C3w": {"type": "window", "global_corners": [[3.25, 13.81, 6.9], [4.25, 13.81, 6.9], [4.25, 13.88, 6.9], [3.25, 13.88, 6.9], [3.25, 13.81, 8.4], [4.25, 13.81, 8.4], [4.25, 13.88, 8.4], [3.25, 13.88, 8.4]], "belongs_to": "1jJ7opRcX6uevup8Hnq0$2"}, "33rbr8lHzC9wyGLDUf1$oL": {"type": "window", "global_corners": [[7.75, 13.81, 6.9], [8.75, 13.81, 6.9], [8.75, 13.88, 6.9], [7.75, 13.88, 6.9], [7.75, 13.81, 8.4], [8.75, 13.81, 8.4], [8.75, 13.88, 8.4], [7.75, 13.88, 8.4]], "belongs_to": "30oDtenHrAwuYDgWTayiN$"}, "0LmvL42xf8o8gvekhf5kDW": {"type": "window", "global_corners": [[6.25, 13.81, 6.9], [7.25, 13.81, 6.9], [7.25, 13.88, 6.9], [6.25, 13.88, 6.9], [6.25, 13.81, 8.4], [7.25, 13.81, 8.4], [7.25, 13.88, 8.4], [6.25, 13.88, 8.4]], "belongs_to": "30oDtenHrAwuYDgWTayiN$"}, "0dAxB0XKHC$QriSRAuBxf6": {"type": "window", "global_corners": [[10.75, 13.81, 6.9], [11.75, 13.81, 6.9], [11.75, 13.88, 6.9], [10.75, 13.88, 6.9], [10.75, 13.81, 8.4], [11.75, 13.81, 8.4], [11.75, 13.88, 8.4], [10.75, 13.88, 8.4]], "belongs_to": "3$PC9MkEH1Ex24UD3VHyzP"}, "3yl6250Yj7yBi59RVKlXKu": {"type": "window", "global_corners": [[9.25, 13.81, 6.9], [10.25, 13.81, 6.9], [10.25, 13.88, 6.9], [9.25, 13.88, 6.9], [9.25, 13.81, 8.4], [10.25, 13.81, 8.4], [10.25, 13.88, 8.4], [9.25, 13.88, 8.4]], "belongs_to": "3$PC9MkEH1Ex24UD3VHyzP"}, "2LrttlMCD93gsPHs8eydhh": {"type": "window", "global_corners": [[13.75, 13.81, 6.9], [14.75, 13.81, 6.9], [14.75, 13.88, 6.9], [13.75, 13.88, 6.9], [13.75, 13.81, 8.4], [14.75, 13.81, 8.4], [14.75, 13.88, 8.4], [13.75, 13.88, 8.4]], "belongs_to": "0Veunyhgf7QxfJXezc1Ydu"}, "0PyP8DIl91dB01H5Na4r6n": {"type": "window", "global_corners": [[12.25, 13.81, 6.9], [13.25, 13.81, 6.9], [13.25, 13.88, 6.9], [12.25, 13.88, 6.9], [12.25, 13.81, 8.4], [13.25, 13.81, 8.4], [13.25, 13.88, 8.4], [12.25, 13.88, 8.4]], "belongs_to": "0Veunyhgf7QxfJXezc1Ydu"}, "0i6DZZR0v0YxdGB37YLlHt": {"type": "window", "global_corners": [[34.75, 2.12, 6.9], [35.75, 2.12, 6.9], [35.75, 2.19, 6.9], [34.75, 2.19, 6.9], [34.75, 2.12, 8.4], [35.75, 2.12, 8.4], [35.75, 2.19, 8.4], [34.75, 2.19, 8.4]], "belongs_to": "1vWhxAiTL1RR3r4R3eC2Vv"}, "2eQ15rBnD9bQnYtYvsSlv$": {"type": "window", "global_corners": [[33.25, 2.12, 6.9], [34.25, 2.12, 6.9], [34.25, 2.19, 6.9], [33.25, 2.19, 6.9], [33.25, 2.12, 8.4], [34.25, 2.12, 8.4], [34.25, 2.19, 8.4], [33.25, 2.19, 8.4]], "belongs_to": "1vWhxAiTL1RR3r4R3eC2Vv"}, "1$pDx4kq9D$Qv87vSmRHF1": {"type": "window", "global_corners": [[31.75, 2.12, 6.9], [32.75, 2.12, 6.9], [32.75, 2.19, 6.9], [31.75, 2.19, 6.9], [31.75, 2.12, 8.4], [32.75, 2.12, 8.4], [32.75, 2.19, 8.4], [31.75, 2.19, 8.4]], "belongs_to": "1vWhxAiTL1RR3r4R3eC2Vv"}, "2MQJI38fb4kxSZGQpeIRXv": {"type": "window", "global_corners": [[30.25, 2.12, 6.9], [31.25, 2.12, 6.9], [31.25, 2.19, 6.9], [30.25, 2.19, 6.9], [30.25, 2.12, 8.4], [31.25, 2.12, 8.4], [31.25, 2.19, 8.4], [30.25, 2.19, 8.4]], "belongs_to": "1vWhxAiTL1RR3r4R3eC2Vv"}, "1OQ6lS92bEv8IU1oObylOf": {"type": "window", "global_corners": [[40.65, 2.12, 6.9], [41.65, 2.12, 6.9], [41.65, 2.19, 6.9], [40.65, 2.19, 6.9], [40.65, 2.12, 8.4], [41.65, 2.12, 8.4], [41.65, 2.19, 8.4], [40.65, 2.19, 8.4]], "belongs_to": "3uvYP4OyH5ufyPIMbZD86h"}, "3cTqMaSBr3wfxDe7CbRYyh": {"type": "window", "global_corners": [[39.25, 2.12, 6.9], [40.25, 2.12, 6.9], [40.25, 2.19, 6.9], [39.25, 2.19, 6.9], [39.25, 2.12, 8.4], [40.25, 2.12, 8.4], [40.25, 2.19, 8.4], [39.25, 2.19, 8.4]], "belongs_to": "3uvYP4OyH5ufyPIMbZD86h"}, "0qcoNAafTDehoCiz4cM6tx": {"type": "window", "global_corners": [[37.75, 2.12, 6.9], [38.75, 2.12, 6.9], [38.75, 2.19, 6.9], [37.75, 2.19, 6.9], [37.75, 2.12, 8.4], [38.75, 2.12, 8.4], [38.75, 2.19, 8.4], [37.75, 2.19, 8.4]], "belongs_to": "3uvYP4OyH5ufyPIMbZD86h"}, "1U75ejClv3dQdMZ31HFglJ": {"type": "window", "global_corners": [[36.25, 2.12, 6.9], [37.25, 2.12, 6.9], [37.25, 2.19, 6.9], [36.25, 2.19, 6.9], [36.25, 2.12, 8.4], [37.25, 2.12, 8.4], [37.25, 2.19, 8.4], [36.25, 2.19, 8.4]], "belongs_to": "3uvYP4OyH5ufyPIMbZD86h"}, "06IfVSEn91UgGayOp3O7IE": {"type": "window", "global_corners": [[28.75, 13.81, 6.9], [29.75, 13.81, 6.9], [29.75, 13.88, 6.9], [28.75, 13.88, 6.9], [28.75, 13.81, 8.4], [29.75, 13.81, 8.4], [29.75, 13.88, 8.4], [28.75, 13.88, 8.4]], "belongs_to": "0oB0YIgnPE49CsBpGIdxOR"}, "2JLDJqS39FHgmOzoWdVdP_": {"type": "window", "global_corners": [[27.25, 13.81, 6.9], [28.25, 13.81, 6.9], [28.25, 13.88, 6.9], [27.25, 13.88, 6.9], [27.25, 13.81, 8.4], [28.25, 13.81, 8.4], [28.25, 13.88, 8.4], [27.25, 13.88, 8.4]], "belongs_to": "0oB0YIgnPE49CsBpGIdxOR"}, "2C5lQ3NhPCegfTg9Z1ac7G": {"type": "window", "global_corners": [[31.75, 13.81, 6.9], [32.75, 13.81, 6.9], [32.75, 13.88, 6.9], [31.75, 13.88, 6.9], [31.75, 13.81, 8.4], [32.75, 13.81, 8.4], [32.75, 13.88, 8.4], [31.75, 13.88, 8.4]], "belongs_to": "3jurQKaejCqgtlRMQvYO$h"}, "31Q_5FuqX07QgicqF9UALl": {"type": "window", "global_corners": [[30.25, 13.81, 6.9], [31.25, 13.81, 6.9], [31.25, 13.88, 6.9], [30.25, 13.88, 6.9], [30.25, 13.81, 8.4], [31.25, 13.81, 8.4], [31.25, 13.88, 8.4], [30.25, 13.88, 8.4]], "belongs_to": "3jurQKaejCqgtlRMQvYO$h"}, "3wtmcFknrEIBf$$ZaZkjsa": {"type": "window", "global_corners": [[34.75, 13.81, 6.9], [35.75, 13.81, 6.9], [35.75, 13.88, 6.9], [34.75, 13.88, 6.9], [34.75, 13.81, 8.4], [35.75, 13.81, 8.4], [35.75, 13.88, 8.4], [34.75, 13.88, 8.4]], "belongs_to": "1I4mvNGj58VPS4IqdvGDOQ"}, "1oYD_Z9ybB_h3cLF0sBrlO": {"type": "window", "global_corners": [[33.25, 13.81, 6.9], [34.25, 13.81, 6.9], [34.25, 13.88, 6.9], [33.25, 13.88, 6.9], [33.25, 13.81, 8.4], [34.25, 13.81, 8.4], [34.25, 13.88, 8.4], [33.25, 13.88, 8.4]], "belongs_to": "1I4mvNGj58VPS4IqdvGDOQ"}, "3u9W_RePLF$fFnvEZnhAA3": {"type": "window", "global_corners": [[37.75, 13.81, 6.9], [38.75, 13.81, 6.9], [38.75, 13.88, 6.9], [37.75, 13.88, 6.9], [37.75, 13.81, 8.4], [38.75, 13.81, 8.4], [38.75, 13.88, 8.4], [37.75, 13.88, 8.4]], "belongs_to": "3BlfjPTqH1qeG63Yox0pCX"}, "1lUbm8UC9BRhi6_rj8flXo": {"type": "window", "global_corners": [[36.25, 13.81, 6.9], [37.25, 13.81, 6.9], [37.25, 13.88, 6.9], [36.25, 13.88, 6.9], [36.25, 13.81, 8.4], [37.25, 13.81, 8.4], [37.25, 13.88, 8.4], [36.25, 13.88, 8.4]], "belongs_to": "3BlfjPTqH1qeG63Yox0pCX"}, "0BEDAo9y13gQ0v5BiWlobp": {"type": "window", "global_corners": [[40.65, 13.81, 6.9], [41.65, 13.81, 6.9], [41.65, 13.88, 6.9], [40.65, 13.88, 6.9], [40.65, 13.81, 8.4], [41.65, 13.81, 8.4], [41.65, 13.88, 8.4], [40.65, 13.88, 8.4]], "belongs_to": "1qHIiTcLf7zwz3pTXujZ3t"}, "1UJnRoYuXDo8ukuFR0M0uj": {"type": "window", "global_corners": [[39.25, 13.81, 6.9], [40.25, 13.81, 6.9], [40.25, 13.88, 6.9], [39.25, 13.88, 6.9], [39.25, 13.81, 8.4], [40.25, 13.81, 8.4], [40.25, 13.88, 8.4], [39.25, 13.88, 8.4]], "belongs_to": "1qHIiTcLf7zwz3pTXujZ3t"}, "2_X97mjPr6SfXHvLlAWVeK": {"type": "window", "global_corners": [[16.75, 13.81, 6.9], [17.75, 13.81, 6.9], [17.75, 13.88, 6.9], [16.75, 13.88, 6.9], [16.75, 13.81, 8.4], [17.75, 13.81, 8.4], [17.75, 13.88, 8.4], [16.75, 13.88, 8.4]], "belongs_to": "0jh6L39QvEQu8mVKX3j43f"}, "3RZiJ6qDzALv1rgqlu1sqF": {"type": "window", "global_corners": [[15.25, 13.81, 6.9], [16.25, 13.81, 6.9], [16.25, 13.88, 6.9], [15.25, 13.88, 6.9], [15.25, 13.81, 8.4], [16.25, 13.81, 8.4], [16.25, 13.88, 8.4], [15.25, 13.88, 8.4]], "belongs_to": "0jh6L39QvEQu8mVKX3j43f"}, "2FZD1g3DX6Lf1xKxpeANT$": {"type": "window", "global_corners": [[0.35, 2.12, 6.9], [1.35, 2.12, 6.9], [1.35, 2.19, 6.9], [0.35, 2.19, 6.9], [0.35, 2.12, 8.4], [1.35, 2.12, 8.4], [1.35, 2.19, 8.4], [0.35, 2.19, 8.4]], "belongs_to": "3zaEFaiGrF1ftyFPQrOe_i"}, "14E0a5PTb3iemHibLOvZOK": {"type": "window", "global_corners": [[4.75, 2.12, 6.9], [5.75, 2.12, 6.9], [5.75, 2.19, 6.9], [4.75, 2.19, 6.9], [4.75, 2.12, 8.4], [5.75, 2.12, 8.4], [5.75, 2.19, 8.4], [4.75, 2.19, 8.4]], "belongs_to": "3zaEFaiGrF1ftyFPQrOe_i"}, "00UNrXETv7oftJb4TQUHq4": {"type": "window", "global_corners": [[3.25, 2.12, 6.9], [4.25, 2.12, 6.9], [4.25, 2.19, 6.9], [3.25, 2.19, 6.9], [3.25, 2.12, 8.4], [4.25, 2.12, 8.4], [4.25, 2.19, 8.4], [3.25, 2.19, 8.4]], "belongs_to": "3zaEFaiGrF1ftyFPQrOe_i"}, "1gxRBxWbf8oRRUychif_cc": {"type": "window", "global_corners": [[1.75, 2.12, 6.9], [2.75, 2.12, 6.9], [2.75, 2.19, 6.9], [1.75, 2.19, 6.9], [1.75, 2.12, 8.4], [2.75, 2.12, 8.4], [2.75, 2.19, 8.4], [1.75, 2.19, 8.4]], "belongs_to": "3zaEFaiGrF1ftyFPQrOe_i"}, "18w4XWKEz1fPVH$dCZCDq2": {"type": "window", "global_corners": [[0.35, 13.81, 6.9], [1.35, 13.81, 6.9], [1.35, 13.88, 6.9], [0.35, 13.88, 6.9], [0.35, 13.81, 8.4], [1.35, 13.81, 8.4], [1.35, 13.88, 8.4], [0.35, 13.88, 8.4]], "belongs_to": "3i9iiZlcT5eQkuRPP$TrLS"}, "1K9shFYpvAiODk_sr0FdfC": {"type": "window", "global_corners": [[1.75, 13.81, 6.9], [2.75, 13.81, 6.9], [2.75, 13.88, 6.9], [1.75, 13.88, 6.9], [1.75, 13.81, 8.4], [2.75, 13.81, 8.4], [2.75, 13.88, 8.4], [1.75, 13.88, 8.4]], "belongs_to": "3i9iiZlcT5eQkuRPP$TrLS"}, "2hwuUNMpz9AAsYWleNcUZN": {"type": "window", "global_corners": [[0.12, 7.55, 6.9], [0.19, 7.55, 6.9], [0.19, 8.45, 6.9], [0.12, 8.45, 6.9], [0.12, 7.55, 8.4], [0.19, 7.55, 8.4], [0.19, 8.45, 8.4], [0.12, 8.45, 8.4]], "belongs_to": "3gYFdGsxTBa9PFlMvRAaiF"}, "2Q31NM555AyhJre_5CK6sQ": {"type": "window", "global_corners": [[41.81, 7.55, 6.9], [41.88, 7.55, 6.9], [41.88, 8.45, 6.9], [41.81, 8.45, 6.9], [41.81, 7.55, 8.4], [41.88, 7.55, 8.4], [41.88, 8.45, 8.4], [41.81, 8.45, 8.4]], "belongs_to": "3CXBDjcSTES8AedjLKSfJe"}}